[{"line":1,"elements":[{"start_timestamp":"2025-02-04T05:21:44.091Z","before":[{"result":{"duration":47467363600,"status":"passed"},"match":{"location":"stepDefinitions.Hooks.setUp()"}}],"line":3,"name":"Validating Email field in the form","description":"","id":"form-validation;validating-email-field-in-the-form","after":[{"result":{"duration":1233078100,"status":"passed"},"match":{"location":"stepDefinitions.Hooks.tearDown()"}}],"type":"scenario","keyword":"Scenario","steps":[{"result":{"duration":110369100,"status":"passed"},"line":4,"name":"opening the url coursera","match":{"location":"stepDefinitions.TC_003_FormValidation.opening_the_url()"},"keyword":"Given "},{"result":{"duration":4463684000,"status":"passed"},"line":5,"name":"click on For Universities","match":{"location":"stepDefinitions.TC_003_FormValidation.click_on_for_universities()"},"keyword":"When "},{"result":{"duration":284542700,"status":"passed"},"line":6,"name":"click on Solutions","match":{"location":"stepDefinitions.TC_003_FormValidation.click_on_solutions()"},"keyword":"And "},{"result":{"duration":1427828100,"status":"passed"},"line":7,"name":"Select any course","match":{"location":"stepDefinitions.TC_003_FormValidation.select_any_course()"},"keyword":"And "},{"result":{"duration":3789514900,"status":"passed"},"line":8,"name":"Filling form with invalid email as \"admin#xyz\"","match":{"arguments":[{"val":"\"admin#xyz\"","offset":35}],"location":"stepDefinitions.TC_003_FormValidation.filling_form_with_invalid_email_as(java.lang.String)"},"keyword":"When "},{"result":{"duration":464417800,"status":"passed"},"line":9,"name":"capturing the error message","match":{"location":"stepDefinitions.TC_003_FormValidation.capturing_the_error_message()"},"keyword":"Then "}]}],"name":"Form Validation","description":"","id":"form-validation","keyword":"Feature","uri":"file:src/test/resources/features/FormValidation.feature","tags":[]},{"line":2,"elements":[{"start_timestamp":"2025-02-04T05:22:43.493Z","before":[{"result":{"duration":8247463600,"status":"passed"},"match":{"location":"stepDefinitions.Hooks.setUp()"}}],"line":4,"name":"Look for Language Learning","description":"","id":"language-learning;look-for-language-learning","after":[{"result":{"duration":1201280800,"status":"passed"},"match":{"location":"stepDefinitions.Hooks.tearDown()"}}],"type":"scenario","keyword":"Scenario","steps":[{"result":{"duration":6009600,"status":"passed"},"line":5,"name":"open the Website again coursera","match":{"location":"stepDefinitions.TC_002_LearningLanguages.open_the_website_again()"},"keyword":"Given "},{"result":{"duration":4030753600,"status":"passed"},"line":6,"name":"Search for \"Language Learning\" in search box","match":{"arguments":[{"val":"\"Language Learning\"","offset":11}],"location":"stepDefinitions.TC_002_LearningLanguages.search_for_in_search_box(java.lang.String)"},"keyword":"And "},{"result":{"duration":239941400,"status":"passed"},"line":7,"name":"Extract all the languages with total count","match":{"location":"stepDefinitions.TC_002_LearningLanguages.extract_all_the_languages_with_total_count()"},"keyword":"And "},{"result":{"duration":18005400,"status":"passed"},"line":8,"name":"Extract  different levels with its total count","match":{"location":"stepDefinitions.TC_002_LearningLanguages.extract_different_levels_with_its_total_count()"},"keyword":"And "},{"result":{"duration":1074454600,"status":"passed"},"line":9,"name":"Display them","match":{"location":"stepDefinitions.TC_002_LearningLanguages.display_them()"},"keyword":"Then "}]}],"name":"Language Learning","description":"","id":"language-learning","keyword":"Feature","uri":"file:src/test/resources/features/LanguageLearning.feature","tags":[]},{"line":2,"elements":[{"start_timestamp":"2025-02-04T05:22:58.329Z","before":[{"result":{"duration":8071812700,"status":"passed"},"match":{"location":"stepDefinitions.Hooks.setUp()"}}],"line":4,"name":"Fetch First two beginner-level web development courses in English language","description":"","id":"identify-web-development-course;fetch-first-two-beginner-level-web-development-courses-in-english-language","after":[{"result":{"duration":1310477400,"status":"passed"},"match":{"location":"stepDefinitions.Hooks.tearDown()"}}],"type":"scenario","keyword":"Scenario","steps":[{"result":{"duration":6256700,"status":"passed"},"line":5,"name":"open the Website coursera","match":{"location":"stepDefinitions.TC_001_WebDevCourses.open_the_Website_coursera()"},"keyword":"Given "},{"result":{"duration":4925091800,"status":"passed"},"line":6,"name":"Search for \"Web Development\" courses","match":{"arguments":[{"val":"\"Web Development\"","offset":11}],"location":"stepDefinitions.TC_001_WebDevCourses.search_for_courses(java.lang.String)"},"keyword":"When "},{"result":{"duration":4745498500,"status":"passed"},"line":7,"name":"filter for Beginners level & English Language courses","match":{"location":"stepDefinitions.TC_001_WebDevCourses.filter_for_beginners_level_english_language_courses()"},"keyword":"And "},{"result":{"duration":393577500,"status":"passed"},"line":8,"name":"extract the course names, total learning hours & rating for first two courses","match":{"location":"stepDefinitions.TC_001_WebDevCourses.extract_the_course_names_total_learning_hours_rating_for_first_two_courses()"},"keyword":"Then "}]}],"name":"Identify Web Development Course","description":"","id":"identify-web-development-course","keyword":"Feature","uri":"file:src/test/resources/features/WebDevelopmentCourses.feature","tags":[]}]]}]